MANIFEST.in
README.md
setup.py
hamlreloader/__init__.py
hamlreloader/reloader.py
hamlreloader.egg-info/PKG-INFO
hamlreloader.egg-info/SOURCES.txt
hamlreloader.egg-info/dependency_links.txt
hamlreloader.egg-info/entry_points.txt
hamlreloader.egg-info/requires.txt
hamlreloader.egg-info/top_level.txt
hamlreloader/tests/__init__.py
hamlreloader/tests/__init__.pyc
hamlreloader/tests/test_reloader.py
hamlreloader/tests/test_reloader.pyc
hamlreloader/tests/sample/render/.nothing
hamlreloader/tests/sample/templates/haml.tmpl
hamlreloader/tests/sample/watch/.nothing