Metadata-Version: 1.1
Name: hamlreloader
Version: 0.0.3
Summary: Dead simple watcher / reloader for HAML
Home-page: http://github.com/petermelias/hamlreloader
Author: Peter M. Elias
Author-email: petermelias@gmail.com
License: MIT
Platform: UNKNOWN
Classifier: Environment :: Web Environment
Classifier: Intended Audience :: Developers
Classifier: License :: OSI Approved :: MIT License
Classifier: Operating System :: OS Independent
Classifier: Programming Language :: Python
Classifier: Topic :: Internet :: WWW/HTTP :: Dynamic Content
Classifier: Topic :: Software Development :: Libraries :: Python Modules
